liveports/__init__.py
liveports/blaster_utils.py
liveports/client.py
liveports/logviewer.html
liveports-0.1.14.dist-info/METADATA
liveports-0.1.14.dist-info/WHEEL
liveports-0.1.14.dist-info/entry_points.txt
liveports-0.1.14.dist-info/top_level.txt
liveports-0.1.14.dist-info/RECORD
