Metadata-Version: 2.1
Name: liveports
Version: 0.1.14
Summary: Give address to your localmachine
Author: Abhinav
Author-email: abhinavabcd@gmail.com
Requires-Dist: brotlipy >=0.7.0
